medface3D/__init__.py
medface3D/demo.py
medface3D/merge_action.py
medface3D/reconstruct.py
medface3D/video_capture.py
medface3D/data/__init__.py
medface3D/data/demo/__init__.py
medface3D/data/sample/face_001.jpg
medface3D/data/sample/face_001.jpg_face_reconstruction.gif
medface3D/data/sample/image00021.jpg
medface3D/data/sample/image00021.jpg_face_reconstruction.gif
medface3D/data/sample/merge_action.jpg
medface3D/data/sample/merge_action.jpg_face_reconstruction.gif
medface3D/simualte/__init__.py
medface3D/simualte/simuator.py
medface3D/utils/__init__.py
medface3D/utils/get_uv_map.py
medface3D/utils/interpolation.py
medface3D/utils/render_mesh.py
medface3D/utils/save_mesh.py
medface3D/utils/transform.py
medface3D/utils/visualize.py
medface3D/worker/__init__.py
medface3D/worker/face_mesh_reconstruction.py
medface3D/worker/face_pose_estimation.py
medface3D/worker/shape_feature_extraction.py
medface3D/worker/texture_extraction.py
medface3d-0.0.2.dist-info/METADATA
medface3d-0.0.2.dist-info/WHEEL
medface3d-0.0.2.dist-info/top_level.txt
medface3d-0.0.2.dist-info/RECORD
