Metadata-Version: 2.1
Name: medface3d
Version: 0.0.2
Summary: 3D face reconstruction using mediapipe 3D Face mesh
Classifier: Programming Language :: Python :: 3
Classifier: Operating System :: OS Independent
Requires-Python: >=3.7
